simplebot_polls/__init__.py
simplebot_polls/orm.py
simplebot_polls/templates/__init__.py
simplebot_polls/templates/poll.j2
simplebot_polls-1.0.0.dist-info/LICENSE
simplebot_polls-1.0.0.dist-info/METADATA
simplebot_polls-1.0.0.dist-info/WHEEL
simplebot_polls-1.0.0.dist-info/entry_points.txt
simplebot_polls-1.0.0.dist-info/top_level.txt
simplebot_polls-1.0.0.dist-info/RECORD
